{
  "users": [
    {
      "name": "admin",
      "email": "admin@mail.com",
      "password": "123456",
      "id": 1
    }
  ],
  "session": [
    {
      "user_id": 1,
      "createSession": "2023-11-04T05:22:50.970Z",
      "id": 1
    },
    {
      "user_id": 1,
      "createSession": "2023-11-04T23:52:39.046Z",
      "id": 2
    },
    {
      "user_id": 1,
      "createSession": "2023-11-05T01:23:20.197Z",
      "id": 3
    },
    {
      "user_id": 1,
      "createSession": "2023-11-05T02:03:52.070Z",
      "id": 4
    },
    {
      "user_id": 1,
      "createSession": "2023-11-05T02:06:48.753Z",
      "id": 5
    },
    {
      "user_id": 1,
      "createSession": "2023-11-05T02:08:27.293Z",
      "id": 6
    }
  ],
  "students": [
    {
      "firstName": "Carlos",
      "lastName": "Perez",
      "age": 28,
      "status": true,
      "id": 1
    },
    {
      "firstName": "Ana",
      "lastName": "Gomez",
      "age": 42,
      "status": false,
      "id": 2
    },
    {
      "firstName": "Juan",
      "lastName": "Lopez",
      "age": 35,
      "status": true,
      "id": 3
    },
    {
      "firstName": "María",
      "lastName": "Martinez",
      "age": 50,
      "status": true,
      "id": 4
    },
    {
      "firstName": "Luis",
      "lastName": "Sanchez",
      "age": 22,
      "status": false,
      "id": 5
    },
    {
      "firstName": "Elena",
      "lastName": "Rodriguez",
      "age": 31,
      "status": true,
      "id": 6
    },
    {
      "firstName": "Pedro",
      "lastName": "Ramirez",
      "age": 40,
      "status": true,
      "id": 7
    },
    {
      "firstName": "Sofia",
      "lastName": "Fernandez",
      "age": 26,
      "status": true,
      "id": 8
    },
    {
      "firstName": "Diego",
      "lastName": "Hernandez",
      "age": 29,
      "status": true,
      "id": 9
    },
    {
      "firstName": "Isabella",
      "lastName": "Garcia",
      "age": 45,
      "status": false,
      "id": 10
    },
    {
      "firstName": "Alejandro",
      "lastName": "Diaz",
      "age": 37,
      "status": true,
      "id": 11
    },
    {
      "firstName": "Carmen",
      "lastName": "Lopez",
      "age": 60,
      "status": true,
      "id": 12
    },
    {
      "firstName": "Miguel",
      "lastName": "Fernandez",
      "age": 33,
      "status": false,
      "id": 13
    },
    {
      "firstName": "Valentina",
      "lastName": "Torres",
      "age": 28,
      "status": true,
      "id": 14
    },
    {
      "firstName": "Jorge",
      "lastName": "Ramirez",
      "age": 55,
      "status": true,
      "id": 15
    },
    {
      "firstName": "Valeria",
      "lastName": "Perez",
      "age": 38,
      "status": false,
      "id": 16
    },
    {
      "firstName": "Roberto",
      "lastName": "Gomez",
      "age": 48,
      "status": true,
      "id": 17
    },
    {
      "firstName": "Alicia",
      "lastName": "Hernandez",
      "age": 31,
      "status": false,
      "id": 18
    },
    {
      "firstName": "Carlos",
      "lastName": "Sanchez",
      "age": 29,
      "status": true,
      "id": 19
    },
    {
      "firstName": "Paula",
      "lastName": "Lopez",
      "age": 47,
      "status": true,
      "id": 20
    },
    {
      "firstName": "Fernando",
      "lastName": "Martinez",
      "age": 34,
      "status": false,
      "id": 21
    },
    {
      "firstName": "Laura",
      "lastName": "Ramirez",
      "age": 25,
      "status": true,
      "id": 22
    },
    {
      "firstName": "Daniel",
      "lastName": "Perez",
      "age": 30,
      "status": false,
      "id": 23
    },
    {
      "firstName": "Patricia",
      "lastName": "Gomez",
      "age": 53,
      "status": true,
      "id": 24
    },
    {
      "firstName": "Ricardo",
      "lastName": "Sanchez",
      "age": 41,
      "status": true,
      "id": 25
    },
    {
      "firstName": "Sara",
      "lastName": "Garcia",
      "age": 27,
      "status": false,
      "id": 26
    },
    {
      "firstName": "Manuel",
      "lastName": "Hernandez",
      "age": 44,
      "status": true,
      "id": 27
    },
    {
      "firstName": "Eva",
      "lastName": "Torres",
      "age": 32,
      "status": true,
      "id": 28
    },
    {
      "firstName": "Carlos",
      "lastName": "Fernandez",
      "age": 39,
      "status": false,
      "id": 29
    },
    {
      "firstName": "Cristina",
      "lastName": "Ramirez",
      "age": 36,
      "status": true,
      "id": 30
    },
    {
      "firstName": "Javier",
      "lastName": "Lopez",
      "age": 56,
      "status": true,
      "id": 31
    },
    {
      "firstName": "Eduardo",
      "lastName": "Gomez",
      "age": 43,
      "status": false,
      "id": 32
    },
    {
      "firstName": "Adriana",
      "lastName": "Perez",
      "age": 30,
      "status": true,
      "id": 33
    },
    {
      "firstName": "Gustavo",
      "lastName": "Sanchez",
      "age": 48,
      "status": true,
      "id": 34
    },
    {
      "firstName": "Natalia",
      "lastName": "Martinez",
      "age": 29,
      "status": false,
      "id": 35
    },
    {
      "firstName": "Hector",
      "lastName": "Hernandez",
      "age": 39,
      "status": true,
      "id": 36
    },
    {
      "firstName": "Silvia",
      "lastName": "Garcia",
      "age": 41,
      "status": false,
      "id": 37
    },
    {
      "firstName": "Oscar",
      "lastName": "Lopez",
      "age": 32,
      "status": true,
      "id": 38
    },
    {
      "firstName": "Lorena",
      "lastName": "Ramirez",
      "age": 47,
      "status": true,
      "id": 39
    },
    {
      "firstName": "Roberto",
      "lastName": "Fernandez",
      "age": 33,
      "status": false,
      "id": 40
    },
    {
      "firstName": "Carmen",
      "lastName": "Gomez",
      "age": 55,
      "status": true,
      "id": 41
    },
    {
      "firstName": "Gonzalo",
      "lastName": "Sanchez",
      "age": 46,
      "status": true,
      "id": 42
    },
    {
      "firstName": "Susana",
      "lastName": "Perez",
      "age": 28,
      "status": false,
      "id": 43
    },
    {
      "firstName": "Lucas",
      "lastName": "Hernandez",
      "age": 37,
      "status": true,
      "id": 44
    },
    {
      "firstName": "Marina",
      "lastName": "Martinez",
      "age": 50,
      "status": true,
      "id": 45
    },
    {
      "firstName": "Ivan",
      "lastName": "Ramirez",
      "age": 36,
      "status": false,
      "id": 46
    },
    {
      "firstName": "Valentina",
      "lastName": "Lopez",
      "age": 25,
      "status": true,
      "id": 47
    },
    {
      "firstName": "Mariano",
      "lastName": "Gomez",
      "age": 34,
      "status": true,
      "id": 48
    },
    {
      "firstName": "Liliana",
      "lastName": "Fernandez",
      "age": 31,
      "status": false,
      "id": 49
    },
    {
      "firstName": "Carlos Alberto",
      "lastName": "Prost",
      "age": 35,
      "status": true,
      "id": 50
    }
  ],
  "teachers": [
    {
      "id": 1,
      "firstName": "Juan",
      "lastName": "Pérez"
    },
    {
      "id": 2,
      "firstName": "María",
      "lastName": "González"
    },
    {
      "id": 3,
      "firstName": "Carlos",
      "lastName": "Rodríguez"
    },
    {
      "id": 4,
      "firstName": "Laura",
      "lastName": "Martínez"
    },
    {
      "id": 5,
      "firstName": "Pedro",
      "lastName": "López"
    },
    {
      "id": 6,
      "firstName": "Ana",
      "lastName": "Díaz"
    },
    {
      "id": 7,
      "firstName": "Miguel",
      "lastName": "Hernández"
    },
    {
      "id": 8,
      "firstName": "Sofía",
      "lastName": "Torres"
    },
    {
      "id": 9,
      "firstName": "Javier",
      "lastName": "Sánchez"
    },
    {
      "id": 10,
      "firstName": "Luis",
      "lastName": "Ramírez"
    },
    {
      "id": 11,
      "firstName": "Carmen",
      "lastName": "Jiménez"
    },
    {
      "id": 12,
      "firstName": "Diego",
      "lastName": "Vargas"
    },
    {
      "id": 13,
      "firstName": "Elena",
      "lastName": "Silva"
    },
    {
      "id": 14,
      "firstName": "Ricardo",
      "lastName": "Mendoza"
    },
    {
      "id": 15,
      "firstName": "Isabel",
      "lastName": "Ortega"
    },
    {
      "id": 16,
      "firstName": "Daniel",
      "lastName": "Castro"
    },
    {
      "id": 17,
      "firstName": "Lucía",
      "lastName": "Guerrero"
    },
    {
      "id": 18,
      "firstName": "Fernando",
      "lastName": "Rojas"
    },
    {
      "id": 19,
      "firstName": "Pilar",
      "lastName": "Luna"
    },
    {
      "id": 20,
      "firstName": "Gabriel",
      "lastName": "Navarro"
    }
  ],
  "courses": [
    {
      "id": 1,
      "name": "Introducción a la Programación",
      "date": "6 de noviembre a 20 de noviembre",
      "hour": "09:00 - 11:00"
    },
    {
      "id": 2,
      "name": "Introducción a la Programación",
      "date": "6 de noviembre a 20 de noviembre",
      "hour": "13:00 - 15:00"
    },
    {
      "id": 3,
      "name": "Introducción a la Programación",
      "date": "6 de noviembre a 20 de noviembre",
      "hour": "20:00 - 22:00"
    },
    {
      "id": 4,
      "name": "Introducción a la Programación",
      "date": "21 de noviembre a 5 de diciembre",
      "hour": "09:00 - 11:00"
    },
    {
      "id": 5,
      "name": "Introducción a la Programación",
      "date": "21 de noviembre a 5 de diciembre",
      "hour": "13:00 - 15:00"
    },
    {
      "id": 6,
      "name": "Introducción a la Programación",
      "date": "21 de noviembre a 5 de diciembre",
      "hour": "20:00 - 22:00"
    },
    {
      "id": 7,
      "name": "Introducción a la Programación",
      "date": "6 de diciembre a 20 de diciembre",
      "hour": "09:00 - 11:00"
    },
    {
      "id": 8,
      "name": "Introducción a la Programación",
      "date": "6 de diciembre a 20 de diciembre",
      "hour": "13:00 - 15:00"
    },
    {
      "id": 9,
      "name": "Introducción a la Programación",
      "date": "6 de diciembre a 20 de diciembre",
      "hour": "20:00 - 22:00"
    },
    {
      "id": 10,
      "name": "Programación Avanzada",
      "date": "6 de noviembre a 20 de noviembre",
      "hour": "09:00 - 11:00"
    },
    {
      "id": 11,
      "name": "Programación Avanzada",
      "date": "6 de noviembre a 20 de noviembre",
      "hour": "13:00 - 15:00"
    },
    {
      "id": 12,
      "name": "Programación Avanzada",
      "date": "6 de noviembre a 20 de noviembre",
      "hour": "20:00 - 22:00"
    },
    {
      "id": 13,
      "name": "Programación Avanzada",
      "date": "21 de noviembre a 5 de diciembre",
      "hour": "09:00 - 11:00"
    },
    {
      "id": 14,
      "name": "Programación Avanzada",
      "date": "21 de noviembre a 5 de diciembre",
      "hour": "13:00 - 15:00"
    },
    {
      "id": 15,
      "name": "Programación Avanzada",
      "date": "21 de noviembre a 5 de diciembre",
      "hour": "20:00 - 22:00"
    },
    {
      "id": 16,
      "name": "Programación Avanzada",
      "date": "6 de diciembre a 20 de diciembre",
      "hour": "09:00 - 11:00"
    },
    {
      "id": 17,
      "name": "Programación Avanzada",
      "date": "6 de diciembre a 20 de diciembre",
      "hour": "13:00 - 15:00"
    },
    {
      "id": 18,
      "name": "Programación Avanzada",
      "date": "6 de diciembre a 20 de diciembre",
      "hour": "20:00 - 22:00"
    },
    {
      "id": 19,
      "name": "Desarrollo Web",
      "date": "6 de noviembre a 20 de noviembre",
      "hour": "09:00 - 11:00"
    },
    {
      "id": 20,
      "name": "Desarrollo Web",
      "date": "6 de noviembre a 20 de noviembre",
      "hour": "13:00 - 15:00"
    },
    {
      "id": 21,
      "name": "Desarrollo Web",
      "date": "6 de noviembre a 20 de noviembre",
      "hour": "20:00 - 22:00"
    },
    {
      "id": 22,
      "name": "Desarrollo Web",
      "date": "21 de noviembre a 5 de diciembre",
      "hour": "09:00 - 11:00"
    },
    {
      "id": 23,
      "name": "Desarrollo Web",
      "date": "21 de noviembre a 5 de diciembre",
      "hour": "13:00 - 15:00"
    },
    {
      "id": 24,
      "name": "Desarrollo Web",
      "date": "21 de noviembre a 5 de diciembre",
      "hour": "20:00 - 22:00"
    },
    {
      "id": 25,
      "name": "Desarrollo Web",
      "date": "6 de diciembre a 20 de diciembre",
      "hour": "09:00 - 11:00"
    },
    {
      "id": 26,
      "name": "Desarrollo Web",
      "date": "6 de diciembre a 20 de diciembre",
      "hour": "13:00 - 15:00"
    },
    {
      "id": 27,
      "name": "Desarrollo Web",
      "date": "6 de diciembre a 20 de diciembre",
      "hour": "20:00 - 22:00"
    },
    {
      "id": 28,
      "name": "Bases de Datos",
      "date": "6 de noviembre a 20 de noviembre",
      "hour": "09:00 - 11:00"
    },
    {
      "id": 29,
      "name": "Bases de Datos",
      "date": "6 de noviembre a 20 de noviembre",
      "hour": "13:00 - 15:00"
    },
    {
      "id": 30,
      "name": "Bases de Datos",
      "date": "6 de noviembre a 20 de noviembre",
      "hour": "20:00 - 22:00"
    },
    {
      "id": 31,
      "name": "Bases de Datos",
      "date": "21 de noviembre a 5 de diciembre",
      "hour": "09:00 - 11:00"
    },
    {
      "id": 32,
      "name": "Bases de Datos",
      "date": "21 de noviembre a 5 de diciembre",
      "hour": "13:00 - 15:00"
    },
    {
      "id": 33,
      "name": "Bases de Datos",
      "date": "21 de noviembre a 5 de diciembre",
      "hour": "20:00 - 22:00"
    },
    {
      "id": 34,
      "name": "Bases de Datos",
      "date": "6 de diciembre a 20 de diciembre",
      "hour": "09:00 - 11:00"
    },
    {
      "id": 35,
      "name": "Bases de Datos",
      "date": "6 de diciembre a 20 de diciembre",
      "hour": "13:00 - 15:00"
    },
    {
      "id": 36,
      "name": "Bases de Datos",
      "date": "6 de diciembre a 20 de diciembre",
      "hour": "20:00 - 22:00"
    },
    {
      "id": 37,
      "name": "Inteligencia Artificial",
      "date": "6 de noviembre a 20 de noviembre",
      "hour": "09:00 - 11:00"
    },
    {
      "id": 38,
      "name": "Inteligencia Artificial",
      "date": "6 de noviembre a 20 de noviembre",
      "hour": "13:00 - 15:00"
    },
    {
      "id": 39,
      "name": "Inteligencia Artificial",
      "date": "6 de noviembre a 20 de noviembre",
      "hour": "20:00 - 22:00"
    },
    {
      "id": 40,
      "name": "Inteligencia Artificial",
      "date": "21 de noviembre a 5 de diciembre",
      "hour": "09:00 - 11:00"
    },
    {
      "id": 41,
      "name": "Inteligencia Artificial",
      "date": "21 de noviembre a 5 de diciembre",
      "hour": "13:00 - 15:00"
    },
    {
      "id": 42,
      "name": "Inteligencia Artificial",
      "date": "21 de noviembre a 5 de diciembre",
      "hour": "20:00 - 22:00"
    },
    {
      "id": 43,
      "name": "Inteligencia Artificial",
      "date": "6 de diciembre a 20 de diciembre",
      "hour": "09:00 - 11:00"
    },
    {
      "id": 44,
      "name": "Inteligencia Artificial",
      "date": "6 de diciembre a 20 de diciembre",
      "hour": "13:00 - 15:00"
    },
    {
      "id": 45,
      "name": "Inteligencia Artificial",
      "date": "6 de diciembre a 20 de diciembre",
      "hour": "20:00 - 22:00"
    },
    {
      "id": 46,
      "name": "Seguridad Informática",
      "date": "6 de noviembre a 20 de noviembre",
      "hour": "09:00 - 11:00"
    },
    {
      "id": 47,
      "name": "Seguridad Informática",
      "date": "6 de noviembre a 20 de noviembre",
      "hour": "13:00 - 15:00"
    },
    {
      "id": 48,
      "name": "Seguridad Informática",
      "date": "6 de noviembre a 20 de noviembre",
      "hour": "20:00 - 22:00"
    },
    {
      "id": 49,
      "name": "Seguridad Informática",
      "date": "21 de noviembre a 5 de diciembre",
      "hour": "09:00 - 11:00"
    },
    {
      "id": 50,
      "name": "Seguridad Informática",
      "date": "21 de noviembre a 5 de diciembre",
      "hour": "13:00 - 15:00"
    },
    {
      "id": 51,
      "name": "Seguridad Informática",
      "date": "21 de noviembre a 5 de diciembre",
      "hour": "20:00 - 22:00"
    },
    {
      "id": 52,
      "name": "Seguridad Informática",
      "date": "6 de diciembre a 20 de diciembre",
      "hour": "09:00 - 11:00"
    },
    {
      "id": 53,
      "name": "Seguridad Informática",
      "date": "6 de diciembre a 20 de diciembre",
      "hour": "13:00 - 15:00"
    },
    {
      "id": 54,
      "name": "Seguridad Informática",
      "date": "6 de diciembre a 20 de diciembre",
      "hour": "20:00 - 22:00"
    }
  ],
  "studentEnrollments": [
    {
      "student_id": 1,
      "course_id": 2,
      "course_name": "Introducción a la Programación",
      "date": "6 de noviembre a 20 de noviembre",
      "hour": "13:00 - 15:00",
      "id": 1
    },
    {
      "student_id": 1,
      "course_id": 11,
      "course_name": "Programación Avanzada",
      "date": "6 de noviembre a 20 de noviembre",
      "hour": "13:00 - 15:00",
      "id": 2
    },
    {
      "student_id": 1,
      "course_id": 36,
      "course_name": "Bases de Datos",
      "date": "6 de diciembre a 20 de diciembre",
      "hour": "20:00 - 22:00",
      "id": 3
    }
  ],
  "teacherEnrollments": []
}